catesegy/__init__.py
catesegy/catesegy.py
catesegy-0.0.1.dist-info/METADATA
catesegy-0.0.1.dist-info/WHEEL
catesegy-0.0.1.dist-info/top_level.txt
catesegy-0.0.1.dist-info/RECORD
