Metadata-Version: 2.1
Name: catesegy
Version: 0.0.1
Summary: Python client for extracting data from CATE archives and writing as segy data
Author-email: Motion Signal Technologies <kit.chambers@motionsignaltechnologies.com>
Project-URL: Homepage, https://github.com/motionsignaltechnologies/cate-segy
Classifier: Programming Language :: Python :: 3
Classifier: License :: OSI Approved :: BSD License
Classifier: Operating System :: OS Independent
Requires-Python: >=3.10
Requires-Dist: numpy (>=1.24.3)
Requires-Dist: requests (>=2.31.0)
Requires-Dist: catenp (>=0.0.9)
Requires-Dist: decorator (>=4.4.2)
Requires-Dist: obsln (>=0.0.3)
